Workbook

Sheet Read Me
A1: OpenOKR user acceptance test
A2: A step-by-step test of the whole product through its screens, done by a person. It follows the order the product is used in: install, invite the team, plan the cycle, draft and publish OKRs, run the week, close the quarter, then the integrations.
A4: The workflow at a glance
A53: How to use this workbook
A54: 1 | B54: Start a fresh instance with an empty database and the staging overlay (docs/install/staging.md). Note the URL.
A55: 2 | B55: Type the shared inbox on the Personas sheet. The seven persona addresses fill themselves in.
A56: 3 | B56: Work down the Test Cases sheet in order. Each module builds on the one before it.
A57: 4 | B57: Sign in as the person in "Login as". Check the Pre-condition, follow the Steps, compare with Expected result.
A58: 5 | B58: Pick a Status from the dropdown. For anything other than Pass, write what you saw in "Actual result / notes".
A59: 6 | B59: For each Fail or Error, add a row on Bug Log with a screenshot link, and put its Bug ID on the test case.
A60: 7 | B60: Read the Summary sheet for the totals. It updates by itself.
A62: Status | B62: When to use it
A63: Not Run | B63: Not tested yet. Every case starts here.
A64: Pass | B64: What you saw matches Expected result.
A65: Fail | B65: The screen works but the result is different from Expected result. Wrong text, wrong number, missing item, a refusal that should not happen.
A66: Error | B66: The app broke: an error page, "We could not load", a blank screen, a spinner that never ends, or a crash.
A67: Blocked | B67: You could not run the test because something earlier failed, or a pre-condition cannot be met. Say which in the notes.
A68: N/A | B68: Does not apply to this instance, for example no Slack workspace or no passkey device.
A70: Before you start
A71: Browsers | B71: One browser profile per persona. Two screens help for M13 and M15, where two people act at once.
A72: Personas | B72: The seven accounts are created by a command after the setup wizard (M02-04), not by hand. They join through a real invitation, and titles, managers and spaces stay empty for M06 and M07.
A73: Email | B73: Every persona address is a plus-address on one inbox, so reset mails reach it once SMTP is set up. Without SMTP the instance prints every mail to its log, and invitation links are also shown once on Admin, Invitations. Mailpit is the quick fix (SMTP on port 1025, inbox at http://localhost:8025).
A74: Server access | B74: A few cases need someone who can read logs, restart the instance or run a pnpm command. They say so in the hint.
A75: AI | B75: AI is off by default and everything before M20 is tested with it off. M20 needs a provider key with a spending limit.
A76: Integrations | B76: M21 to M26 need outside accounts (Slack, Teams, WhatsApp, Telegram, an identity provider, an MCP client). Mark N/A for any you do not have.
A77: Never | B77: Paste an API key, a token or a real person's password into this workbook. The one shared password on Personas belongs to test accounts on the staging instance only.
A79: Known risks found while writing this
A80: Publishing | B80: Code review suggests gates 2 and 5 have no field in the UI. M11-05 tests it. If they cannot turn green, publish with the override in M11-07.
A81: Sessions | B81: Sessions cannot be created from the UI. The only weekly session is the one the starter template makes in M02. Quarterly reviews may not be reachable at all (M18-06).
A82: Admins | B82: Only the first account has full access, and no screen grants it to anyone else.
A83: Chat test | B83: "Send me a test" on Admin, Channels sends an email, not a chat message.
A84: 2FA | B84: There is no button to turn one-time codes off. Use the throwaway persona Amara.
A86: Generated from docs/testing/uat-cases.mjs and uat-guide.mjs. 193 test cases across 26 modules.

Sheet Module Guide
A1: Module guide
A2: What each module is for and how it flows, in the order to test it. The Test Cases sheet has the detailed steps; this sheet is the map.
A4: Module | B4: Phase | C4: What it proves | D4: Screens | E4: Who signs in | F4: Workflow | G4: Needs first | H4: Leaves ready for later | I4: Setup needed | J4: Time (min)
A5: M01 Install and first account | B5: 1. Set up | C5: Turn an empty server into an instance with one owner | D5: /setup, /setup/account, /sign-up | E5: Admin | F5: 1. Open the instance and get sent to setup 2. Name the instance Northwind Labs 3. Create the owner account 4. Check that registration is now closed | G5: Nothing. Start here | H5: An owner account. Everybody after this joins by invitation | I5: A fresh instance with an empty database | J5: 10
A6: M02 Welcome wizard | B6: 1. Set up | C6: Give the new workspace its name, clock, rhythm and starting content | D6: /welcome | E6: Admin | F6: 1. Name the workspace and pick its timezone 2. Choose the check-in rhythm 3. Skip the invite 4. Apply the OKR starter cycle template 5. Land on the work map 6. Operator runs deploy/staging/seed.sh for the seven personas 7. One persona signs in | G6: M01 | H6: A current cycle, one objective with 3 key results, a KPI, a KPI tree, the weekly session M15 needs, and seven persona accounts | I6: Someone with shell access to the staging host for the seed step | J6: 20
A7: M03 Workspace settings | B7: 1. Set up | C7: Check that workspace settings save, reload and reset | D7: Admin: General, Branding, Rhythm and thresholds | E7: Admin | F7: 1. Change timezone and language 2. Check the mail warning 3. Set a brand colour 4. Set the check-in rhythm 5. Rename a concept, then set it back | G7: M02 | H7: The rhythm every later reminder and due date follows | I7: Nothing extra | J7: 15
A8: M04 Invitations | B8: 2. Build the team | C8: Check the invitation path with spare people, since the personas were seeded | D8: Admin, Invitations; /join/<token>; /sign-up | E8: Admin, then spare addresses | F8: 1. Admin invites +leaver personally 2. Test Leaver opens the link and signs up 3. A wrong address is refused 4. A shared link admits +guest1 and +guest2 5. A domain outside the list is refused 6. Revoked and made-up links are refused | G8: M02 | H8: Test Leaver, the spare account M19 erases | I8: The shared inbox and a private browser window | J8: 15
A9: M05 Sign-in and account security | B9: 2. Build the team | C9: Prove sign-in, password reset and the second factor protect an account | D9: /sign-in, /forgot-password, /reset-password, /backup-code, Account, Security | E9: Jonas, Mei, Amara, Sara, Priya | F9: 1. Refuse a wrong password 2. Reset a forgotten password by mail 3. Turn on one-time codes for Amara 4. Sign in with a code and with a backup code 5. Add a passkey 6. Revoke another device | G9: M02 | H9: Confidence that accounts are safe before real data goes in | I9: Mailpit or SMTP for the reset mail. An authenticator app | J9: 30
A10: M06 People and org chart | B10: 2. Build the team | C10: Give everyone a title and a manager so the org chart is real | D10: People, People / <person> | E10: Admin, Mei, Jonas, Tomas | F10: 1. Admin sets title and manager for each persona 2. Check the org chart 3. A loop in the chain is refused 4. Members edit only their own profile 5. Suspend and restore Tomas | G10: M02 | H10: Reporting lines, used by the org chart and by who reviews whom | I10: Nothing extra | J10: 20
A11: M07 Spaces | B11: 2. Build the team | C11: Create the team homes that own goals, boards and sessions | D11: Spaces, Spaces / <space> | E11: Admin, Priya, Amara, Jonas | F11: 1. Admin creates Product, Sales and Customer Success 2. Priya adds members with roles 3. A member joins and leaves 4. A non-manager cannot manage 5. Change settings, archive a spare space | G11: M06 | H11: Spaces that goals, the board and the weekly session belong to | I11: Nothing extra | J11: 20
A12: M08 Cycle: prepare, diagnose, direction | B12: 3. Plan the cycle | C12: Walk the first three phases so drafting has something to stand on | D12: Cycle (phases 1 to 3), Cycles card | E12: Admin, Priya | F12: 1. Read the eight-phase rail 2. Create the next cycle and set the publication deadline 3. Phase 1: sponsor, facilitator, input pack 4. Phase 2: rank three strategic issues 5. Phase 3: choose a priority | G12: M07 | H12: A priority for objectives to contribute to, and the deadline gate 6 checks | I12: Nothing extra | J12: 25
A13: M09 Drafting OKRs and quality checks | B13: 3. Plan the cycle | C13: Draft objectives and key results while the quality checks fire live | D13: Cycle, phase 4; /method/<rule> | E13: Sara, Daniel, Tomas | F13: 1. Draft Sara's objective with champion and reviewer 2. Type weak wording and watch OBJ-1 and OBJ-2 fire 3. Open a rule card and the method page 4. Add key results, weak then measurable 5. Record a current value 6. Daniel and Tomas draft their own | G13: M08 | H13: A draft set of objectives for three teams | I13: AI off | J13: 40
A14: M10 Goal page and documents | B14: 3. Plan the cycle | C14: Work on one goal: values, confidence, comments, documents and files | D14: Goals, Goals / <goal>, Documents / <doc> | E14: Sara, Priya, Mei, Jonas | F14: 1. Open the goal and read its header 2. Update values and confidence 3. Comment and watch 4. Start a private document, then publish two versions 5. Attach and detach a file 6. Filter the explorer | G14: M09 | H14: A goal with history, discussion and a document | I14: A small PDF to attach | J14: 30
A15: M11 Alignment and publishing | B15: 3. Plan the cycle | C15: Align the set and publish it through the six gates | D15: Goals, Alignment studio; Cycle, phase 5 | E15: Priya, Admin | F15: 1. Look at the cascade 2. Link a team goal to the company goal 3. Record and confirm a dependency 4. Read each gate and follow its fix 5. Publish, or override with a reason 6. Check a member cannot publish | G15: M10 | H15: A published set. The cycle moves to phase 6 and check-ins start | I15: Nothing extra | J15: 30
A16: M12 KPIs and recovery | B16: 4. Run the cycle | C16: Track KPIs continuously and recover one that falls out of its corridor | D16: KPIs grid, KPIs / <kpi>, Trees, Recovery board | E16: Priya, Admin | F16: 1. Add a KPI 2. Enter values and watch green, amber and red 3. Build a formula and a tree 4. Let a KPI drop to red 5. Launch a recovery objective 6. Move a threshold and see colours change | G16: M11 | H16: A recovering KPI with its own objective | I16: Nothing extra | J16: 30
... A30: M26 Cloud operator console | B30: 6. Integrations | C30: Check the managed-cloud operator console | D30: /operator, /operator/<workspace>, /operator/instance, Admin, Support access | E30: Operator, Admin, Sara | F30: 1. Console is hidden on self-hosted 2. Operator lists workspaces 3. Suspend and restore a workspace 4. Ask for and approve support access 5. Show an instance banner | G30: M04 | H30: Cloud operations checked | I30: OPENOKR_CLOUD=true and an operator granted with pnpm cloud:operator | J30: 30
A31: Total time | J31: =SUM(J5:J30)

Sheet Summary
A1: Test summary
A2: Every number below is a formula over the Test Cases sheet. Set the Status column there and this page updates.
A4: Module | B4: Cases | C4: Pass | D4: Fail | E4: Error | F4: Blocked | G4: N/A | H4: Not run | I4: Executed | J4: Pass rate
A5: M01 Install and first account | B5: =COUNTIF('Test Cases'!$B:$B,$A5) | C5: =COUNTIFS('Test Cases'!$B:$B,$A5,'Test Cases'!$J:$J,"Pass") | D5: =COUNTIFS('Test Cases'!$B:$B,$A5,'Test Cases'!$J:$J,"Fail") | E5: =COUNTIFS('Test Cases'!$B:$B,$A5,'Test Cases'!$J:$J,"Error") | F5: =COUNTIFS('Test Cases'!$B:$B,$A5,'Test Cases'!$J:$J,"Blocked") | G5: =COUNTIFS('Test Cases'!$B:$B,$A5,'Test Cases'!$J:$J,"N/A") | H5: =B5-SUM(C5:G5) | I5: =C5+D5+E5 | J5: =IF(I5=0,"",C5/I5)
A6: M02 Welcome wizard | B6: =COUNTIF('Test Cases'!$B:$B,$A6) | C6: =COUNTIFS('Test Cases'!$B:$B,$A6,'Test Cases'!$J:$J,"Pass") | D6: =COUNTIFS('Test Cases'!$B:$B,$A6,'Test Cases'!$J:$J,"Fail") | E6: =COUNTIFS('Test Cases'!$B:$B,$A6,'Test Cases'!$J:$J,"Error") | F6: =COUNTIFS('Test Cases'!$B:$B,$A6,'Test Cases'!$J:$J,"Blocked") | G6: =COUNTIFS('Test Cases'!$B:$B,$A6,'Test Cases'!$J:$J,"N/A") | H6: =B6-SUM(C6:G6) | I6: =C6+D6+E6 | J6: =IF(I6=0,"",C6/I6)
A7: M03 Workspace settings | B7: =COUNTIF('Test Cases'!$B:$B,$A7) | C7: =COUNTIFS('Test Cases'!$B:$B,$A7,'Test Cases'!$J:$J,"Pass") | D7: =COUNTIFS('Test Cases'!$B:$B,$A7,'Test Cases'!$J:$J,"Fail") | E7: =COUNTIFS('Test Cases'!$B:$B,$A7,'Test Cases'!$J:$J,"Error") | F7: =COUNTIFS('Test Cases'!$B:$B,$A7,'Test Cases'!$J:$J,"Blocked") | G7: =COUNTIFS('Test Cases'!$B:$B,$A7,'Test Cases'!$J:$J,"N/A") | H7: =B7-SUM(C7:G7) | I7: =C7+D7+E7 | J7: =IF(I7=0,"",C7/I7)
A8: M04 Invitations | B8: =COUNTIF('Test Cases'!$B:$B,$A8) | C8: =COUNTIFS('Test Cases'!$B:$B,$A8,'Test Cases'!$J:$J,"Pass") | D8: =COUNTIFS('Test Cases'!$B:$B,$A8,'Test Cases'!$J:$J,"Fail") | E8: =COUNTIFS('Test Cases'!$B:$B,$A8,'Test Cases'!$J:$J,"Error") | F8: =COUNTIFS('Test Cases'!$B:$B,$A8,'Test Cases'!$J:$J,"Blocked") | G8: =COUNTIFS('Test Cases'!$B:$B,$A8,'Test Cases'!$J:$J,"N/A") | H8: =B8-SUM(C8:G8) | I8: =C8+D8+E8 | J8: =IF(I8=0,"",C8/I8)
A9: M05 Sign-in and account security | B9: =COUNTIF('Test Cases'!$B:$B,$A9) | C9: =COUNTIFS('Test Cases'!$B:$B,$A9,'Test Cases'!$J:$J,"Pass") | D9: =COUNTIFS('Test Cases'!$B:$B,$A9,'Test Cases'!$J:$J,"Fail") | E9: =COUNTIFS('Test Cases'!$B:$B,$A9,'Test Cases'!$J:$J,"Error") | F9: =COUNTIFS('Test Cases'!$B:$B,$A9,'Test Cases'!$J:$J,"Blocked") | G9: =COUNTIFS('Test Cases'!$B:$B,$A9,'Test Cases'!$J:$J,"N/A") | H9: =B9-SUM(C9:G9) | I9: =C9+D9+E9 | J9: =IF(I9=0,"",C9/I9)
A10: M06 People and org chart | B10: =COUNTIF('Test Cases'!$B:$B,$A10) | C10: =COUNTIFS('Test Cases'!$B:$B,$A10,'Test Cases'!$J:$J,"Pass") | D10: =COUNTIFS('Test Cases'!$B:$B,$A10,'Test Cases'!$J:$J,"Fail") | E10: =COUNTIFS('Test Cases'!$B:$B,$A10,'Test Cases'!$J:$J,"Error") | F10: =COUNTIFS('Test Cases'!$B:$B,$A10,'Test Cases'!$J:$J,"Blocked") | G10: =COUNTIFS('Test Cases'!$B:$B,$A10,'Test Cases'!$J:$J,"N/A") | H10: =B10-SUM(C10:G10) | I10: =C10+D10+E10 | J10: =IF(I10=0,"",C10/I10)
A11: M07 Spaces | B11: =COUNTIF('Test Cases'!$B:$B,$A11) | C11: =COUNTIFS('Test Cases'!$B:$B,$A11,'Test Cases'!$J:$J,"Pass") | D11: =COUNTIFS('Test Cases'!$B:$B,$A11,'Test Cases'!$J:$J,"Fail") | E11: =COUNTIFS('Test Cases'!$B:$B,$A11,'Test Cases'!$J:$J,"Error") | F11: =COUNTIFS('Test Cases'!$B:$B,$A11,'Test Cases'!$J:$J,"Blocked") | G11: =COUNTIFS('Test Cases'!$B:$B,$A11,'Test Cases'!$J:$J,"N/A") | H11: =B11-SUM(C11:G11) | I11: =C11+D11+E11 | J11: =IF(I11=0,"",C11/I11)
A12: M08 Cycle: prepare, diagnose, direction | B12: =COUNTIF('Test Cases'!$B:$B,$A12) | C12: =COUNTIFS('Test Cases'!$B:$B,$A12,'Test Cases'!$J:$J,"Pass") | D12: =COUNTIFS('Test Cases'!$B:$B,$A12,'Test Cases'!$J:$J,"Fail") | E12: =COUNTIFS('Test Cases'!$B:$B,$A12,'Test Cases'!$J:$J,"Error") | F12: =COUNTIFS('Test Cases'!$B:$B,$A12,'Test Cases'!$J:$J,"Blocked") | G12: =COUNTIFS('Test Cases'!$B:$B,$A12,'Test Cases'!$J:$J,"N/A") | H12: =B12-SUM(C12:G12) | I12: =C12+D12+E12 | J12: =IF(I12=0,"",C12/I12)
A13: M09 Drafting OKRs and quality checks | B13: =COUNTIF('Test Cases'!$B:$B,$A13) | C13: =COUNTIFS('Test Cases'!$B:$B,$A13,'Test Cases'!$J:$J,"Pass") | D13: =COUNTIFS('Test Cases'!$B:$B,$A13,'Test Cases'!$J:$J,"Fail") | E13: =COUNTIFS('Test Cases'!$B:$B,$A13,'Test Cases'!$J:$J,"Error") | F13: =COUNTIFS('Test Cases'!$B:$B,$A13,'Test Cases'!$J:$J,"Blocked") | G13: =COUNTIFS('Test Cases'!$B:$B,$A13,'Test Cases'!$J:$J,"N/A") | H13: =B13-SUM(C13:G13) | I13: =C13+D13+E13 | J13: =IF(I13=0,"",C13/I13)
A14: M10 Goal page and documents | B14: =COUNTIF('Test Cases'!$B:$B,$A14) | C14: =COUNTIFS('Test Cases'!$B:$B,$A14,'Test Cases'!$J:$J,"Pass") | D14: =COUNTIFS('Test Cases'!$B:$B,$A14,'Test Cases'!$J:$J,"Fail") | E14: =COUNTIFS('Test Cases'!$B:$B,$A14,'Test Cases'!$J:$J,"Error") | F14: =COUNTIFS('Test Cases'!$B:$B,$A14,'Test Cases'!$J:$J,"Blocked") | G14: =COUNTIFS('Test Cases'!$B:$B,$A14,'Test Cases'!$J:$J,"N/A") | H14: =B14-SUM(C14:G14) | I14: =C14+D14+E14 | J14: =IF(I14=0,"",C14/I14)
A15: M11 Alignment and publishing | B15: =COUNTIF('Test Cases'!$B:$B,$A15) | C15: =COUNTIFS('Test Cases'!$B:$B,$A15,'Test Cases'!$J:$J,"Pass") | D15: =COUNTIFS('Test Cases'!$B:$B,$A15,'Test Cases'!$J:$J,"Fail") | E15: =COUNTIFS('Test Cases'!$B:$B,$A15,'Test Cases'!$J:$J,"Error") | F15: =COUNTIFS('Test Cases'!$B:$B,$A15,'Test Cases'!$J:$J,"Blocked") | G15: =COUNTIFS('Test Cases'!$B:$B,$A15,'Test Cases'!$J:$J,"N/A") | H15: =B15-SUM(C15:G15) | I15: =C15+D15+E15 | J15: =IF(I15=0,"",C15/I15)
A16: M12 KPIs and recovery | B16: =COUNTIF('Test Cases'!$B:$B,$A16) | C16: =COUNTIFS('Test Cases'!$B:$B,$A16,'Test Cases'!$J:$J,"Pass") | D16: =COUNTIFS('Test Cases'!$B:$B,$A16,'Test Cases'!$J:$J,"Fail") | E16: =COUNTIFS('Test Cases'!$B:$B,$A16,'Test Cases'!$J:$J,"Error") | F16: =COUNTIFS('Test Cases'!$B:$B,$A16,'Test Cases'!$J:$J,"Blocked") | G16: =COUNTIFS('Test Cases'!$B:$B,$A16,'Test Cases'!$J:$J,"N/A") | H16: =B16-SUM(C16:G16) | I16: =C16+D16+E16 | J16: =IF(I16=0,"",C16/I16)
... A30: M26 Cloud operator console | B30: =COUNTIF('Test Cases'!$B:$B,$A30) | C30: =COUNTIFS('Test Cases'!$B:$B,$A30,'Test Cases'!$J:$J,"Pass") | D30: =COUNTIFS('Test Cases'!$B:$B,$A30,'Test Cases'!$J:$J,"Fail") | E30: =COUNTIFS('Test Cases'!$B:$B,$A30,'Test Cases'!$J:$J,"Error") | F30: =COUNTIFS('Test Cases'!$B:$B,$A30,'Test Cases'!$J:$J,"Blocked") | G30: =COUNTIFS('Test Cases'!$B:$B,$A30,'Test Cases'!$J:$J,"N/A") | H30: =B30-SUM(C30:G30) | I30: =C30+D30+E30 | J30: =IF(I30=0,"",C30/I30)
A31: Total | B31: =SUM(B5:B30) | C31: =SUM(C5:C30) | D31: =SUM(D5:D30) | E31: =SUM(E5:E30) | F31: =SUM(F5:F30) | G31: =SUM(G5:G30) | H31: =SUM(H5:H30) | I31: =SUM(I5:I30) | J31: =IF(I31=0,"",C31/I31)
A33: Executed counts Pass, Fail and Error. Pass rate is Pass divided by Executed. Blocked and N/A are left out of the rate because nothing was judged. A blank Status counts as Not run.

Sheet Personas
A1: Personas
A2: The Northwind Labs cast from the product's own demo story. Every test case names who to sign in as. Type the shared inbox in the yellow cell below: the seven addresses fill themselves in, and sh deploy/staging/seed.sh --inbox <that inbox> creates exactly those accounts (M02-04).
A4: Shared inbox | C4: For example qa.okr@gmail.com. No plus sign: each persona adds its own.
A5: Shared password | B5: northwind-uat-2026 | C5: The seed command's default. Change it here if the command was run with --password.
A7: Persona | B7: Full name | C7: Title | D7: Reports to | E7: Sign-in email | F7: Password | G7: Access and role in the test | H7: Used in
A8: Admin | B8: (your own name) | C8: Chief Executive | D8: Nobody | G8: Full access. The first account. The only one who can open Admin screens | H8: All
A9: Priya | B9: Priya Raman | C9: Chief Product Officer | D9: Admin | E9: =IF($B$4="","",LOWER(SUBSTITUTE($B$4,"@","+priya@"))) | F9: =$B$5 | G9: Member (edit). Manager of the Product space. Reviewer of Sara's goal | H9: M02, M06, M07, M11, M14, M15
A10: Daniel | B10: Daniel Osei | C10: VP Sales | D10: Admin | E10: =IF($B$4="","",LOWER(SUBSTITUTE($B$4,"@","+daniel@"))) | F10: =$B$5 | G10: Member (edit). Manager of the Sales space. Champion of the sales objective | H10: M06, M07, M09
A11: Tomas | B11: Tomás Herrera | C11: Head of Customer Success | D11: Admin | E11: =IF($B$4="","",LOWER(SUBSTITUTE($B$4,"@","+tomas@"))) | F11: =$B$5 | G11: Member (edit). Manager of the Customer Success space. Used for suspend and restore | H11: M06, M07, M09
A12: Mei | B12: Mei Lin | C12: Head of Engineering | D12: Priya | E12: =IF($B$4="","",LOWER(SUBSTITUTE($B$4,"@","+mei@"))) | F12: =$B$5 | G12: Member (edit). Owns initiatives. Used as the wrong reviewer | H12: M05, M06, M13, M14
A13: Sara | B13: Sara Nasser | C13: Product Manager, Onboarding | D13: Priya | E13: =IF($B$4="","",LOWER(SUBSTITUTE($B$4,"@","+sara@"))) | F13: =$B$5 | G13: Member (edit). Champion of the onboarding objective. Does the check-ins | H13: M09, M14, M15
A14: Jonas | B14: Jonas Weber | C14: Account Executive | D14: Daniel | E14: =IF($B$4="","",LOWER(SUBSTITUTE($B$4,"@","+jonas@"))) | F14: =$B$5 | G14: Member (edit). Used for the 'cannot do this' checks | H14: M05, M06, M07, M14, M19
A15: Amara | B15: Amara Diallo | C15: Data Analyst | D15: Admin | E15: =IF($B$4="","",LOWER(SUBSTITUTE($B$4,"@","+amara@"))) | F15: =$B$5 | G15: Member (edit). Throwaway account for 2FA and guest tests | H15: M05, M19
A17: Spare addresses for M04 and M19 use the same inbox: +leaver, +wrong, +other, +guest1, +guest2. Use one browser profile per persona (Chrome profiles, Firefox containers or separate browsers); it lets two people act at once in M13 and M15.

Sheet Test Cases
A1: ID | B1: Module | C1: Test case | D1: Login as | E1: Pre-condition | F1: Steps | G1: Expected result | H1: Priority | I1: Hint for the tester | J1: Status | K1: Actual result / notes | L1: Tester | M1: Date | N1: Bug ID
A2: M01 Install and first account: Turn an empty server into an instance with one owner. About 10 min. Full workflow on the Module Guide sheet.
A3: M01-01 | B3: M01 Install and first account | C3: An empty instance sends every visitor to setup | D3: Nobody (signed out) | E3: Fresh instance, empty database, no account yet | F3: 1. Open the instance URL followed by /sign-in | G3: Redirected to /setup. Heading "Set up OpenOKR". The "This deployment" section lists the connection checks. Button "Create the first account" is shown | H3: High | J3: Not Run
A4: M01-02 | B4: M01 Install and first account | C4: A short password is refused on the first account | D4: Admin | E4: M01-01 done | F4: 1. Click "Create the first account" 2. Fill "Your name" and "Email" 3. Type an 8-character password 4. Click "Finish setup" | G4: The form refuses the password and points at the 12-character minimum. No account is created | H4: Medium | J4: Not Run
A5: M01-03 | B5: M01 Install and first account | C5: Create the first account | D5: Admin | E5: M01-02 done | F5: 1. Set "What should this instance be called?" to Northwind Labs 2. Fill your own name, your email and a password of 12 or more characters 3. Click "Finish setup" | G5: Button reads "Setting up..." then you land on /welcome with heading "Set up your workspace" | H5: High | I5: Write down the email and password. This is the only full-access account for the whole test | J5: Not Run
A6: M01-04 | B6: M01 Install and first account | C6: Registration closes once the first account exists | D6: Nobody (signed out) | E6: M01-03 done. Use a private browser window | F6: 1. Open /sign-up 2. Open /setup | G6: /sign-up shows "Registration is closed" with "Back to sign in". /setup shows "Setup is already done" with "Go to the instance" | H6: High | J6: Not Run
A7: M02 Welcome wizard: Give the new workspace its name, clock, rhythm and starting content. Needs M01 first. About 20 min. Full workflow on the Module Guide sheet.
A8: M02-01 | B8: M02 Welcome wizard | C8: Walk the welcome wizard with the starter template | D8: Admin | E8: Signed in right after M01-03 | F8: 1. Workspace name: Northwind Labs. Click "Continue" 2. Pick your timezone. Check-in frequency: "Weekly". Click "Continue" 3. Invite step: click "Skip" 4. Template step: choose "OKR starter cycle" and click "Use this template" 5. Worked example step: click "Start empty" | G8: The wizard closes and the work map opens. It shows the objective "Make onboarding the reason new customers stay" with 3 key results | H8: High | I8: Skip the invite here. An invite sent from the wizard never shows its link on screen. M04 invites everybody from Admin, Invitations instead | J8: Not Run
A9: M02-02 | B9: M02 Welcome wizard | C9: The template created its KPI, space content and session | D9: Admin | E9: M02-01 done | F9: 1. Open KPIs 2. Open KPIs, Trees 3. Open Sessions | G9: KPIs shows "30-day retention" under category Customer. Trees shows a tree named Retention. Sessions shows "Weekly session" under "Ahead" with the chip "You facilitate" | H9: High | I9: This weekly session is the only one M15 can use. The UI has no way to create another | J9: Not Run
A10: M02-03 | B10: M02 Welcome wizard | C10: The wizard does not come back | D10: Admin | E10: M02-01 done | F10: 1. Sign out and sign in again 2. Open /welcome directly | G10: Sign-in lands on the work map. /welcome redirects to / | H10: Medium | J10: Not Run
A11: M02-04 | B11: M02 Welcome wizard | C11: Create the seven persona accounts | D11: Admin (server access) | E11: M02-01 done. The stack runs with deploy/staging/compose.staging.yaml | F11: 1. On the staging host run: sh deploy/staging/seed.sh --inbox <the inbox on Personas> 2. Read the list it prints 3. Open People 4. Open Admin, Invitations | G11: The command prints seven addresses and the password. People lists all seven with no title and no manager. Invitations shows one workspace link, 7 uses, status "Revoked" | H11: High | I11: Run it once. A second run changes nothing. It refuses a workspace that already has other people in it | J11: Not Run
A12: M02-05 | B12: M02 Welcome wizard | C12: A persona can sign in | D12: Priya | E12: M02-04 done. A private window | F12: 1. Sign in with Priya's address from Personas and the shared password | G12: Priya lands on the work map of Northwind Labs, not on the welcome wizard | H12: High | J12: Not Run
A13: M03 Workspace settings: Check that workspace settings save, reload and reset. Needs M02 first. About 15 min. Full workflow on the Module Guide sheet.
A14: M03-01 | B14: M03 Workspace settings | C14: Save and reload general settings | D14: Admin | E14: Signed in | F14: 1. Open Admin, General 2. Set "Timezone" and "Language" 3. Click "Save" 4. Reload the page | G14: The values you saved are still there after the reload | H14: High | J14: Not Run
A15: M03-02 | B15: M03 Workspace settings | C15: The console mail warning is visible | D15: Admin | E15: Instance has no SMTP settings | F15: 1. Open Admin, General | G15: A banner says "Every message is going to the log, not to anybody" | H15: Medium | I15: If SMTP or Mailpit is already set up, mark N/A | J15: Not Run
A16: M03-03 | B16: M03 Workspace settings | C16: Reset general settings to defaults | D16: Admin | E16: M03-01 done | F16: 1. Change a value 2. Click "Reset to defaults" 3. Confirm | G16: Every field returns to its default value | H16: Low | J16: Not Run
A17: M03-04 | B17: M03 Workspace settings | C17: Brand colour applies across the app | D17: Admin | E17: Signed in | F17: 1. Open Admin, Branding 2. Type #336699 in "Primary colour (hex)" 3. Click "Save" 4. Open the work map 5. Try the value blue and save | G17: The primary colour changes on buttons and links. The value blue is refused with a message. Write the message in Actual result | H17: Low | J17: Not Run
A18: M03-05 | B18: M03 Workspace settings | C18: Rhythm settings show the value in force | D18: Admin | E18: Signed in | F18: 1. Open Admin, Rhythm and thresholds 2. Look at each group card 3. Set "Check-in frequency" to weekly and "Anchor day" to Monday 4. Click "Save" | G18: Every field shows "in force: <value>". After saving, the new values show as in force | H18: High | J18: Not Run
A19: M03-06 | B19: M03 Workspace settings | C19: Rename a concept in Terminology | D19: Admin | E19: Signed in | F19: 1. Open Admin, Rhythm and thresholds, Terminology 2. Rename Objective to Goal (singular and plural) 3. Save and open the work map 4. Set it back afterwards | G19: Screens use the new word. After setting it back, the old word returns | H19: Low | J19: Not Run
A20: M04 Invitations: Check the invitation path with spare people, since the personas were seeded. Needs M02 first. About 15 min. Full workflow on the Module Guide sheet.
A21: M04-01 | B21: M04 Invitations | C21: Send a personal invitation | D21: Admin | E21: M02-04 done. Spare address: the inbox from Personas with +leaver | F21: 1. Open Admin, Invitations 2. In "Invite one person" type the +leaver address 3. Keep "Expires in days" at 14 4. Click "Create the invitation" | G21: A box says "Copy this now. It is not shown again." and shows the link. The "Issued" card lists the row with status "Open" | H21: High | I21: Copy the link into a notepad. With SMTP set up the mail also arrives in the shared inbox | J21: Not Run
A22: M04-02 | B22: M04 Invitations | C22: Accept an invitation as a new person | D22: Test Leaver (spare) | E22: M04-01 done. Use a private window | F22: 1. Open the invitation link 2. Click "Create an account" 3. Sign up with the +leaver address, name Test Leaver, and a 12+ character password | G22: The join page says "You have been invited to Northwind Labs". After sign-up Test Leaver is inside the workspace. On Admin, Invitations the row now shows "Used up" | H22: High | I22: Keep this account. M19-05 erases it | J22: Not Run
A23: M04-03 | B23: M04 Invitations | C23: An invitation refuses a different email address | D23: Nobody (signed out) | E23: Admin created a personal invitation for the +wrong address | F23: 1. Open that link in a private window 2. Click "Create an account" 3. Sign up with the +other address instead | G23: The page warns "This invitation was issued to a different address, so it will be refused" and joining is refused | H23: High | J23: Not Run
A24: M04-04 | B24: M04 Invitations | C24: Invite people with a shared link | D24: Admin | E24: Signed in | F24: 1. In "Create a link to share" set "Maximum uses" to 2 and "Allowed domains" to the inbox's domain 2. Click "Create the link" 3. Open the link twice in separate private windows and sign up as +guest1 and +guest2 | G24: Both join. The row shows 2 uses and then "Used up" | H24: High | I24: The seven personas were not invited this way, so their sign-in is tested in M05, not here | J24: Not Run
A25: M04-05 | B25: M04 Invitations | C25: A shared link refuses a domain outside the list | D25: Nobody (signed out) | E25: M04-04 link still has uses left, or create a new one | F25: 1. Open the link 2. Sign up with an email from another domain | G25: Joining is refused. No new member appears in People | H25: Medium | J25: Not Run
A26: M04-06 | B26: M04 Invitations | C26: Revoke an invitation | D26: Admin | E26: Signed in | F26: 1. Create a personal invitation for a spare email 2. Click "Revoke" on its row and confirm 3. Open the revoked link in a private window | G26: The row shows "Revoked". The link page says "That invitation cannot be used" with "Sign in instead" | H26: High | J26: Not Run
A27: M04-07 | B27: M04 Invitations | C27: A made-up invitation link is refused | D27: Nobody (signed out) | E27: None | F27: 1. Open /join/abc123 | G27: "That invitation cannot be used" | H27: Low | J27: Not Run
A28: M05 Sign-in and account security: Prove sign-in, password reset and the second factor protect an account. Needs M02 first. About 30 min. Full workflow on the Module Guide sheet.
A29: M05-01 | B29: M05 Sign-in and account security | C29: Wrong password is refused | D29: Jonas | E29: Signed out | F29: 1. Open /sign-in 2. Type Jonas's email and a wrong password 3. Click "Sign in" | G29: "Those details did not match. Check them and try again." | H29: High | J29: Not Run
A30: M05-02 | B30: M05 Sign-in and account security | C30: Sign in and sign out | D30: Jonas | E30: Signed out | F30: 1. Sign in with the right password 2. Sign out | G30: Sign-in lands on the work map. Sign-out returns to the sign-in page. Pressing Back does not show workspace data | H30: High | J30: Not Run
A31: M05-03 | B31: M05 Sign-in and account security | C31: Reset a forgotten password | D31: Mei | E31: Signed out. SMTP or Mailpit set up, and access to the shared inbox | F31: 1. Click "Forgot your password?" 2. Type Mei's email and click "Send reset link" 3. Open the reset link from the mail 4. Type a new password in "New password" and click "Set password" 5. Sign in with the new password | G31: "Check your email" appears. The link opens "Choose a new password". Sign-in works with the new password and not with the old one | H31: High | I31: The mail goes to the +mei plus-address, so it lands in the shared inbox. Without SMTP it is only in the server log | J31: Not Run
A32: M05-04 | B32: M05 Sign-in and account security | C32: A used reset link cannot be used again | D32: Mei | E32: M05-03 done | F32: 1. Open the same reset link again 2. Try to set a password | G32: "That link has expired or was already used. Ask for a new one." | H32: Medium | J32: Not Run
A33: M05-05 | B33: M05 Sign-in and account security | C33: Turn on one-time codes (2FA) | D33: Amara | E33: Signed in. An authenticator app that accepts a pasted otpauth link (Google Authenticator, 1Password, Authy) | F33: 1. Open Account, Security 2. Type the password in "Confirm your password" and click "Set up one-time codes" 3. Add the shown otpauth text to the authenticator app 4. Save the backup codes somewhere 5. Type the code in "Code from your app" and click "Turn on" | G33: 2FA is on. The backup codes were shown once | H33: High | I33: The screen shows text, not a QR code. There is no button to turn 2FA off again, so use Amara only | J33: Not Run
A34: M05-06 | B34: M05 Sign-in and account security | C34: Sign in with a one-time code | D34: Amara | E34: M05-05 done. Signed out | F34: 1. Sign in with email and password 2. On "Enter your code" type a wrong code and click "Verify" 3. Type the right code and click "Verify" | G34: Wrong code: "That code was not right. Codes change every 30 seconds." Right code: signed in | H34: High | J34: Not Run
A35: M05-07 | B35: M05 Sign-in and account security | C35: Sign in with a backup code, once only | D35: Amara | E35: M05-05 done. Signed out | F35: 1. Sign in with email and password 2. Open the "backup code page" link 3. Enter one backup code and click "Verify" 4. Sign out and try the same backup code again | G35: First use signs in. Second use: "That backup code was not recognised, or it has been used." | H35: Medium | J35: Not Run
A36: M05-08 | B36: M05 Sign-in and account security | C36: Add a passkey and sign in with it | D36: Sara | E36: A device with Windows Hello, Touch ID or a security key | F36: 1. Open Account, Security, click "Add a passkey" 2. Sign out 3. Click "Sign in with a passkey" | G36: The passkey is listed. Sign-in with it works without a password | H36: Low | I36: Mark N/A if the device has no passkey support | J36: Not Run
A37: M05-09 | B37: M05 Sign-in and account security | C37: Revoke another signed-in device | D37: Priya | E37: Priya signed in on two browsers | F37: 1. In browser 1 open Account, Security, Sessions 2. Click "Revoke" on the other device 3. Reload browser 2 | G37: Browser 2 is signed out | H37: Medium | J37: Not Run
A38: M05-10 | B38: M05 Sign-in and account security | C38: Too many sign-in attempts are slowed down | D38: Jonas | E38: Signed out | F38: 1. Try a wrong password about 10 times quickly | G38: "Too many attempts. Wait a minute and try again." | H38: Low | J38: Not Run
A39: M06 People and org chart: Give everyone a title and a manager so the org chart is real. Needs M02 first. About 20 min. Full workflow on the Module Guide sheet.
A40: M06-01 | B40: M06 People and org chart | C40: Set titles and managers for the cast | D40: Admin | E40: All 7 personas joined | F40: 1. Open People, click each persona 2. In "Edit member (admin)" set "Title" and "Manager" from the Personas sheet 3. Click "Save" for each | G40: Each profile shows the title and manager you set | H40: High | J40: Not Run
A41: M06-02 | B41: M06 People and org chart | C41: The org chart draws the reporting lines | D41: Admin | E41: M06-01 done | F41: 1. Open People, tab "Org chart" | G41: Admin at the top. Priya with Mei and Sara under her. Daniel with Jonas. Tomas and Amara directly under Admin | H41: High | J41: Not Run
A42: M06-03 | B42: M06 People and org chart | C42: A manager loop is refused | D42: Admin | E42: M06-01 done | F42: 1. Open your own profile as Admin 2. Set "Manager" to Sara and save | G42: "That would make a manager chain that loops back on itself." | H42: Medium | J42: Not Run
A43: M06-04 | B43: M06 People and org chart | C43: Search the directory | D43: Jonas | E43: M06-01 done | F43: 1. Open People 2. Type Engineering in "Search by name or title" 3. Type zzz | G43: Engineering finds Mei. zzz shows "No members match your search." | H43: Medium | J43: Not Run
A44: M06-05 | B44: M06 People and org chart | C44: The two agents are members | D44: Jonas | E44: None | F44: 1. Open People, tab "Directory" | G44: OKR Coach and OKR Champion are listed as members | H44: Medium | J44: Not Run
A45: M06-06 | B45: M06 People and org chart | C45: A member edits their own profile only | D45: Mei | E45: Signed in as Mei | F45: 1. Open your own profile, click "Edit your profile" 2. Set Timezone to Asia/Singapore and write a bio, save 3. Open Priya's profile | G45: Mei's profile saves. Priya's profile has no edit controls | H45: High | J45: Not Run
A46: M06-07 | B46: M06 People and org chart | C46: Suspend and restore a member | D46: Admin, then Tomas | E46: M06-01 done | F46: 1. Open Tomas's profile, card "Lifecycle", click "Suspend" 2. In Tomas's browser, reload and try to sign in 3. As Admin click "Restore" | G46: Tomas shows the badge "Suspended" and cannot use the workspace. After "Restore" Tomas works again | H46: High | I46: Write in Actual result exactly what Tomas sees while suspended | J46: Not Run
A47: M06-08 | B47: M06 People and org chart | C47: The last full-access member cannot suspend themselves | D47: Admin | E47: None | F47: 1. Open your own profile, click "Suspend" | G47: "This is the only member with full access to the workspace. Give someone else full access first." | H47: Medium | J47: Not Run
A48: M07 Spaces: Create the team homes that own goals, boards and sessions. Needs M06 first. About 20 min. Full workflow on the Module Guide sheet.
A49: M07-01 | B49: M07 Spaces | C49: Create the team spaces | D49: Admin | E49: M06-01 done | F49: 1. Open Spaces 2. In "Create a space" create Product (manager Priya), Sales (manager Daniel) and Customer Success (manager Tomas), each with a mission 3. Click "Create the space" for each | G49: The three spaces are listed with their managers | H49: High | J49: Not Run
A50: M07-02 | B50: M07 Spaces | C50: Add members to a space with a role | D50: Priya | E50: M07-01 done. Priya is the Product manager | F50: 1. Open Spaces, Product 2. In "Manage this space" click "Add somebody" 3. Add Sara "As" Coordinator and Mei "As" Member | G50: "Members (n)" goes up and shows each person's role | H50: High | J50: Not Run
A51: M07-03 | B51: M07 Spaces | C51: Join and leave a space | D51: Amara | E51: M07-01 done | F51: 1. Open Spaces, Product, click "Join" 2. Click "Leave" 3. Click "Rejoin" | G51: The member count and the button change each time | H51: Medium | J51: Not Run
A52: M07-04 | B52: M07 Spaces | C52: Only a manager can manage a space | D52: Jonas | E52: M07-01 done | F52: 1. Open Spaces, Product | G52: No "Manage this space" card and no "Space settings" card | H52: High | J52: Not Run
A53: M07-05 | B53: M07 Spaces | C53: Change space settings | D53: Priya | E53: M07-01 done | F53: 1. Open Spaces, Product, card "Space settings" 2. Change "Coaching strictness" and "Default check-in frequency" 3. Click "Save space settings" and reload | G53: The new values stay after reload | H53: Medium | J53: Not Run
A54: M07-06 | B54: M07 Spaces | C54: Archive a space | D54: Admin | E54: None | F54: 1. Create a space named Temp 2. Open it and click "Archive this space" 3. Go back to Spaces | G54: Temp is gone from the list | H54: Low | J54: Not Run
A55: M08 Cycle: prepare, diagnose, direction: Walk the first three phases so drafting has something to stand on. Needs M07 first. About 25 min. Full workflow on the Module Guide sheet.
A56: M08-01 | B56: M08 Cycle: prepare, diagnose, direction | C56: The cycle screen shows the eight phases | D56: Admin | E56: M02 done | F56: 1. Open Cycle | G56: Rail "The cycle" lists phases 0 to 7 with a chip "<done> of <n> done". Phase 0 says "Annual cycles only". The phase header says "completion is computed, never self-reported" | H56: High | J56: Not Run
A57: M08-02 | B57: M08 Cycle: prepare, diagnose, direction | C57: Create the next cycle and set the publication deadline | D57: Admin | E57: None | F57: 1. On Cycle find the "Cycles" card 2. In "Create the cycle containing this date" pick a date in next quarter and click "Create" 3. In "Publication deadline" pick a date before the current cycle's first day and click "Save" | G57: The next cycle exists in the cycle picker. The deadline is saved | H57: High | I57: Gate 6 needs the deadline to be before day one of the cycle. For the current cycle that is a date in the past | J57: Not Run
A58: M08-03 | B58: M08 Cycle: prepare, diagnose, direction | C58: Phase 1 Prepare: complete the input pack | D58: Admin | E58: None | F58: 1. Open Cycle, phase 1 2. Name the sponsor (Admin) and the facilitator (Priya) 3. Mark each of the 7 input-pack items as gathered 4. Mark the pack as distributed | G58: "Still needed here" empties and phase 1 shows done on the rail | H58: High | J58: Not Run
A59: M08-04 | B59: M08 Cycle: prepare, diagnose, direction | C59: Phase 2 Diagnose: rank three issues | D59: Priya | E59: Phase 1 done | F59: 1. Open Cycle, phase 2 2. Before adding anything read the empty state 3. Add 3 issues in "The issue" with a "Rank" 4. Record the baseline and declare this the first cycle if asked | G59: Empty state says "Nothing is on the list yet. At least 3 ranked issues are needed". After adding, the issues are listed in rank order and phase 2 shows done | H59: High | J59: Not Run
A60: M08-05 | B60: M08 Cycle: prepare, diagnose, direction | C60: Phase 3 Direction: choose a priority | D60: Priya | E60: Phase 2 done | F60: 1. Open Cycle, phase 3 2. Add "The priority", "The success statement" and "The issue this answers" | G60: The priority is listed and phase 3 shows done | H60: High | J60: Not Run
A61: M08-06 | B61: M08 Cycle: prepare, diagnose, direction | C61: A later phase warns about missing earlier work | D61: Admin | E61: Use the next cycle from M08-02 where phase 1 is not done | F61: 1. Switch the cycle picker to the next cycle 2. Open phase 4 | G61: Warning "This phase is blocked by earlier work" with "Go and gather what is missing". The forms can still be used | H61: Medium | J61: Not Run
A62: M09 Drafting OKRs and quality checks: Draft objectives and key results while the quality checks fire live. Needs M08 first. About 40 min. Full workflow on the Module Guide sheet.
A63: M09-01 | B63: M09 Drafting OKRs and quality checks | C63: An objective needs a title | D63: Sara | E63: Cycle phase 4 open on the current cycle | F63: 1. In "Draft an objective" leave the title empty 2. Click "Add objective" | G63: "An objective needs a sentence saying what changes." | H63: Medium | J63: Not Run
A64: M09-02 | B64: M09 Drafting OKRs and quality checks | C64: Draft an objective | D64: Sara | E64: None | F64: 1. Title: Make onboarding something new customers finish by themselves 2. Contribution: the phase 3 priority 3. Level team, Champion Sara, Reviewer Priya 4. Click "Add objective" | G64: An objective card appears with the field "Objective, checked as you type" | H64: High | J64: Not Run
A65: M09-03 | B65: M09 Drafting OKRs and quality checks | C65: Output wording fires OBJ-1 | D65: Sara | E65: M09-02 done | F65: 1. In "Objective, checked as you type" type: Launch the new onboarding flow | G65: A red chip "1 rule firing" and a chip "OBJ-1 · Outcome, not output". The strength meter drops. Nothing is saved | H65: High | J65: Not Run
A66: M09-04 | B66: M09 Drafting OKRs and quality checks | C66: A metric in the objective fires two rules | D66: Sara | E66: M09-02 done | F66: 1. Type: Increase revenue by 20% | G66: OBJ-1 FAIL and "OBJ-2 · Inspiring and directional" WARN. The meter shows the pass, warn and fail counts | H66: High | J66: Not Run
A67: M09-05 | B67: M09 Drafting OKRs and quality checks | C67: A one-word objective warns | D67: Sara | E67: M09-02 done | F67: 1. Type: Grow 2. Click the OBJ-2 chip | G67: The rule card shows WARN and the prompt "Very short. Would someone outside your team understand where you are headed and why it matters?" | H67: Medium | J67: Not Run
A68: M09-06 | B68: M09 Drafting OKRs and quality checks | C68: A good objective passes every check | D68: Sara | E68: M09-02 done | F68: 1. Type: Make onboarding something new customers finish by themselves | G68: No rule firing on the objective | H68: High | J68: Not Run
A69: M09-07 | B69: M09 Drafting OKRs and quality checks | C69: The rule card links to the method | D69: Sara | E69: A rule chip is showing | F69: 1. Click a rule chip 2. Click "See the rule in METHOD" 3. Click "Back to the cycle" | G69: Card shows the verdict, "What was seen" and weak and strong examples. The method page shows "How it judges, in order". Back returns to the cycle | H69: Medium | J69: Not Run
A70: M09-08 | B70: M09 Drafting OKRs and quality checks | C70: A key result needs numbers | D70: Sara | E70: M09-02 done | F70: 1. In the key result form type: Improve self-serve onboarding 2. Leave "Baseline" and "Target" empty 3. Click "Add key result" | G70: "A key result needs a baseline and a target, both as numbers." | H70: High | J70: Not Run
A71: M09-09 | B71: M09 Drafting OKRs and quality checks | C71: Effort wording fires KR-5 | D71: Sara | E71: M09-02 done | F71: 1. Add key result: Hold 12 customer workshops, baseline 0, target 12 | G71: "KR-5 · Impact, not effort" FAIL on that key result | H71: High | J71: Not Run
A72: M09-10 | B72: M09 Drafting OKRs and quality checks | C72: Add measurable key results | D72: Sara | E72: M09-02 done | F72: 1. Add: Raise self-serve completion from 40% to 70%, baseline 40, target 70, unit % 2. Look at KR-1 3. Add a second one: Cut support tickets per new account from 5 to 2, direction reduce | G72: With one key result KR-1 warns "Can a single measure prove this from every angle?". With two it stops warning | H72: High | J72: Not Run
A73: M09-11 | B73: M09 Drafting OKRs and quality checks | C73: Record where a key result is now | D73: Sara | E73: M09-10 done | F73: 1. In "Where is it now?" type 45 and click "Record" | G73: Progress on that key result moves from the baseline | H73: Medium | J73: Not Run
A74: M09-12 | B74: M09 Drafting OKRs and quality checks | C74: The quality panel lists every open issue | D74: Sara | E74: Some rules still firing | F74: 1. Look at the right rail "Quality panel" 2. Click one issue | G74: It says "<n> issues across <m> objectives". Clicking jumps to the field that fixes it | H74: Medium | J74: Not Run
... A76: M09-14 | B76: M09 Drafting OKRs and quality checks | C76: AI buttons are hidden with AI off | D76: Sara | E76: No AI provider set up | F76: 1. Look at the drafting surface | G76: No "Draft from an ambition", "Suggest a parent" or "Suggest numbers" | H76: Medium | J76: Not Run
A77: M10 Goal page and documents: Work on one goal: values, confidence, comments, documents and files. Needs M09 first. About 30 min. Full workflow on the Module Guide sheet.
A78: M10-01 | B78: M10 Goal page and documents | C78: Open a goal and read its header | D78: Sara | E78: M09 done | F78: 1. Open Goals, click Sara's objective | G78: Header shows level, "Sara champions it, Priya reviews it", weight, a health chip and "Next check-in due" | H78: High | J78: Not Run
A79: M10-02 | B79: M10 Goal page and documents | C79: Update a key result value and confidence | D79: Sara | E79: M10-01 done | F79: 1. Under "Key results (n)" change a value and move the confidence slider 2. Click "Save" 3. Reload | G79: The new value and confidence stay after reload. Progress changes | H79: High | J79: Not Run
A80: M10-03 | B80: M10 Goal page and documents | C80: Edit the goal, and an empty title is refused | D80: Sara | E80: M10-01 done | F80: 1. Open Edit, change "Weight" to 2, save 2. Clear the title and save | G80: The weight saves. Empty title: "An objective needs a title." | H80: Medium | J80: Not Run
A81: M10-04 | B81: M10 Goal page and documents | C81: Comment on a goal | D81: Priya | E81: M10-01 done | F81: 1. Open Sara's goal 2. Write in "Write a comment..." and post it | G81: The comment shows under "Discussion (1)" with Priya's name. Sara gets it in the Inbox | H81: Medium | J81: Not Run
A82: M10-05 | B82: M10 Goal page and documents | C82: Watch a goal | D82: Mei | E82: None | F82: 1. Open Sara's goal and click Watch 2. Click it again | G82: The control switches between watching and not watching | H82: Low | J82: Not Run
A83: M10-06 | B83: M10 Goal page and documents | C83: Start a draft document | D83: Sara | E83: M10-01 done | F83: 1. In the goal's "Documents" card type How we will win activation in "Start a document" 2. Click "Start" 3. Type text. Use / to add a heading and a bullet list 4. Click "Save" | G83: The document opens with the banner "Only you can see this". After saving: "Saved. Not published yet." | H83: High | J83: Not Run
A84: M10-07 | B84: M10 Goal page and documents | C84: A draft document is private | D84: Priya | E84: M10-06 done | F84: 1. Open Sara's goal, Documents card 2. Search for activation | G84: Priya does not see or find Sara's draft | H84: High | J84: Not Run
A85: M10-08 | B85: M10 Goal page and documents | C85: Publish a document and a second version | D85: Sara | E85: M10-06 done | F85: 1. Click "Publish" 2. Edit a line and click "Publish a new version" 3. Open the "History" rail and compare the versions | G85: History shows "2 versions". The diff shows added and removed lines. Priya can now open it | H85: High | J85: Not Run
A86: M10-09 | B86: M10 Goal page and documents | C86: Attach, download and detach a file | D86: Sara | E86: A published document | F86: 1. In "Files" click "Attach" with no file chosen 2. Choose a small PDF and click "Attach" 3. Click the file name to download it 4. Click "Detach" | G86: No file: "Choose a file first." Then the file is listed with its size, downloads correctly, and disappears after Detach | H86: Medium | I86: Also try a file over 8 MB and write what happens | J86: Not Run
A87: M10-10 | B87: M10 Goal page and documents | C87: Filter the goals explorer | D87: Jonas | E87: M09 done | F87: 1. Open Goals 2. Set "Whose" to Mine, then Everyone's 3. Set "View" to Tree, then List 4. Pick a "Level" with no goals | G87: The list follows each filter. No match shows "No goals match this view." | H87: Medium | J87: Not Run
A88: M11 Alignment and publishing: Align the set and publish it through the six gates. Needs M10 first. About 30 min. Full workflow on the Module Guide sheet.
A89: M11-01 | B89: M11 Alignment and publishing | C89: The alignment studio draws the cascade | D89: Priya | E89: M09 done | F89: 1. Open Goals, tab "Alignment studio" 2. Use "Zoom in", "Zoom out" and "Reset" 3. Click a goal on the canvas | G89: Goals are drawn as a tree. Unaligned ones carry a marker. Clicking shows the side tabs details, health and review | H89: Medium | J89: Not Run
A90: M11-02 | B90: M11 Alignment and publishing | C90: Link two goals | D90: Priya | E90: M11-01 done | F90: 1. Click "Link two goals" 2. Click Sara's objective, then the company objective | G90: A line joins them. "Alignment health" changes on the health tab | H90: High | J90: Not Run
A91: M11-03 | B91: M11 Alignment and publishing | C91: Record and confirm a dependency | D91: Priya | E91: Cycle phase 5 open | F91: 1. In "Record a dependency" pick a key result that depends on another team 2. Click "Add to the register" 3. Click "Confirm" | G91: The dependency is listed as confirmed | H91: Medium | J91: Not Run
A92: M11-04 | B92: M11 Alignment and publishing | C92: The six publish gates explain what is missing | D92: Admin | E92: Cycle phase 5 open | F92: 1. Read "Publish gates" 2. Click each red gate's fix link | G92: Chip "<n> of 6 green". Each red gate lists its reasons. Each fix link opens the place that fixes it | H92: High | I92: Gate 6 link opens Admin, Rhythm, but the deadline field is on the Cycles card of the Cycle screen. Log it if confusing | J92: Not Run
A93: M11-05 | B93: M11 Alignment and publishing | C93: Turn all six gates green | D93: Admin | E93: M11-04 done | F93: 1. Follow every gate's fix until each one is green | G93: "6 of 6 green" and "Publish the set" becomes clickable | H93: High | I93: Code review found no field for a key result's owner and due date (gate 2) and no field for 'what was cut' (gate 5). If they cannot go green, mark Fail and log it | J93: Not Run
A94: M11-06 | B94: M11 Alignment and publishing | C94: Publish is disabled while a gate is red | D94: Admin | E94: At least one gate red | F94: 1. Look at "Publish the set" | G94: Button disabled. Text: "All six gates have to be green. A gate nobody can judge counts against publication." | H94: High | J94: Not Run
A95: M11-07 | B95: M11 Alignment and publishing | C95: Override needs a real reason | D95: Admin | E95: At least one gate red | F95: 1. Expand "Publish anyway, past the red gates" 2. Type a reason under 20 characters 3. Type a reason of 20+ characters and click "Override and publish" | G95: Short reason is blocked. Long reason publishes: "Published <date>." and the cycle moves to phase 6 | H95: High | J95: Not Run
A96: M11-08 | B96: M11 Alignment and publishing | C96: Only the admin can publish | D96: Priya | E96: Before publishing | F96: 1. Open Cycle, phase 5 | G96: "Publishing is a workspace administrator's call." No publish button | H96: High | J96: Not Run
A97: M12 KPIs and recovery: Track KPIs continuously and recover one that falls out of its corridor. Needs M11 first. About 30 min. Full workflow on the Module Guide sheet.
A98: M12-01 | B98: M12 KPIs and recovery | C98: Add a KPI | D98: Priya | E98: None | F98: 1. Open KPIs, card "Add a KPI" 2. Click "Add" with an empty title 3. Title Test NPS, Frequency monthly, Better when higher, Standing target 100, click "Add" | G98: Empty: "A KPI needs a title. What is being measured?" Then Test NPS appears in the grid | H98: High | J98: Not Run
A99: M12-02 | B99: M12 KPIs and recovery | C99: Values colour by the health corridor | D99: Priya | E99: M12-01 done | F99: 1. In the current period cell of Test NPS type 95 and press Enter 2. Change it to 80 3. Change it to 60 | G99: 95 green and healthy. 80 amber and watch. 60 red and unhealthy. "Now" shows the percentage | H99: High | J99: Not Run
A100: M12-03 | B100: M12 KPIs and recovery | C100: Lower-is-better KPI reverses the maths | D100: Priya | E100: None | F100: 1. Add KPI Support backlog, Better when lower, target 100 2. Enter 125 | G100: Amber, 80%, watch | H100: Medium | J100: Not Run
A101: M12-04 | B101: M12 KPIs and recovery | C101: Grid refuses text and handles clearing | D101: Priya | E101: M12-01 done | F101: 1. Type abc in a cell and press Enter 2. Clear a cell and press Enter 3. Type a value and press Esc | G101: abc: "A value has to be a number, or empty to clear it." Clearing shows no data. Esc restores the old value | H101: Medium | J101: Not Run
...

Sheet Bug Log
A1: Bug ID | B1: Test ID | C1: Module | D1: Title | E1: Severity | F1: Steps to reproduce | G1: Expected | H1: Actual | I1: Screenshot or video link | J1: Browser and device | K1: Reported by | L1: Date | M1: Status
A2: BUG-001 | B2: M09-03 | C2: M09 Drafting OKRs and quality checks | D2: Example row, replace it: OBJ-1 chip missing | E2: Major | F2: 1. Open Cycle, phase 4 2. Type Launch the new onboarding flow | G2: OBJ-1 chip shows | H2: No chip, meter stays green | I2: https://link-to-screenshot | J2: Chrome 140, Windows 11 | K2: Tester name | L2: 2026-09-25 | M2: Open
